nlpyper/__init__.py
nlpyper/base_module.py
nlpyper/batch_source_module.py
nlpyper/docs_by_field_module.py
nlpyper/module.py
nlpyper/multi_doc_module.py
nlpyper/pipeline.py
nlpyper/single_doc_module.py
nlpyper-0.0.3.dist-info/LICENSE
nlpyper-0.0.3.dist-info/METADATA
nlpyper-0.0.3.dist-info/WHEEL
nlpyper-0.0.3.dist-info/top_level.txt
nlpyper-0.0.3.dist-info/RECORD
